tap_feed/__init__.py
tap_feed/streams.py
tap_feed/tap.py
tap_feed/tests/__init__.py
tap_feed/tests/parser/__init__.py
tap_feed/tests/parser/test_atom_1_0.py
tap_feed/tests/parser/test_rss_2_0.py
tap_feed/tests/test_core.py
tap_feed/tests/test_dynamic_schema.py
tap_feed/tests/test_tap.py
tap_feed-1.1.1.dist-info/entry_points.txt
tap_feed-1.1.1.dist-info/LICENSE
tap_feed-1.1.1.dist-info/WHEEL
tap_feed-1.1.1.dist-info/METADATA
tap_feed-1.1.1.dist-info/RECORD
