Metadata-Version: 2.1
Name: tap-feed
Version: 1.1.1
Summary: A Singer tap for RSS and Atom feeds built with the Meltano SDK for Singer Taps.
Home-page: https://github.com/jawats/tap-feed
License: Apache-2.0
Keywords: ELT,feed,RSS,Atom
Author: Jon Watson
Requires-Python: >=3.7.1,<3.11
Classifier: License :: OSI Approved :: Apache Software License
Classifier: Programming Language :: Python :: 3
Classifier: Programming Language :: Python :: 3.10
Classifier: Programming Language :: Python :: 3.8
Classifier: Programming Language :: Python :: 3.9
Requires-Dist: feedparser (>=6.0.8,<7.0.0)
Requires-Dist: requests (>=2.25.1,<3.0.0)
Requires-Dist: singer-sdk (>=0.8.0,<0.9.0)
Project-URL: Repository, https://github.com/jawats/tap-feed
